ufo_sm/__init__.py
ufo_sm/build_restrict.py
ufo_sm/coupling_orders.py
ufo_sm/couplings.py
ufo_sm/decays.py
ufo_sm/function_library.py
ufo_sm/lorentz.py
ufo_sm/object_library.py
ufo_sm/parameters.py
ufo_sm/particles.py
ufo_sm/py3_model.pkl
ufo_sm/restrict_c_mass.dat
ufo_sm/restrict_ckm.dat
ufo_sm/restrict_default.dat
ufo_sm/restrict_lepton_masses.dat
ufo_sm/restrict_no_b_mass.dat
ufo_sm/restrict_no_masses.dat
ufo_sm/restrict_no_tau_mass.dat
ufo_sm/restrict_no_widths.dat
ufo_sm/restrict_zeromass_ckm.dat
ufo_sm/vertices.py
ufo_sm/write_param_card.py
ufo_sm-1.0.0.dist-info/WHEEL
ufo_sm-1.0.0.dist-info/METADATA
ufo_sm-1.0.0.dist-info/RECORD
