Metadata-Version: 2.1
Name: ufo-sm
Version: 1.0.0
Summary: Standard Model UFO
Home-page: https://github.com/APN-Pucky/feynml
Author: Alexander Puck Neuwirth
Author-email: alexander@neuwirth-informatik.de
Requires-Python: >=3.8,<4.0
Classifier: Programming Language :: Python :: 3
Classifier: Programming Language :: Python :: 3.8
Classifier: Programming Language :: Python :: 3.9
Classifier: Programming Language :: Python :: 3.10
Classifier: Programming Language :: Python :: 3.11
Project-URL: Repository, https://github.com/APN-Pucky/feynml
